MANIFEST.in
account_assert_test.xml
account_bank_view.xml
account_end_fy.xml
account_financial_report_data.xml
account_installer.xml
account_invoice_view.xml
account_invoice_workflow.xml
account_menuitem.xml
account_pre_install.yml
account_report.xml
account_unit_test.xml
account_view.xml
board_account_view.xml
company_view.xml
ir_sequence_view.xml
partner_view.xml
product_view.xml
res_config_view.xml
setup.py
./__init__.py
./__openerp__.py
./account.py
./account_analytic_line.py
./account_bank.py
./account_bank_statement.py
./account_cash_statement.py
./account_financial_report.py
./account_invoice.py
./account_move_line.py
./company.py
./installer.py
./ir_sequence.py
./partner.py
./product.py
./res_config.py
./res_currency.py
./edi/__init__.py
./edi/invoice.py
./project/__init__.py
./project/project.py
./project/report/__init__.py
./project/report/account_journal.py
./project/report/analytic_balance.py
./project/report/analytic_journal.py
./project/report/cost_ledger.py
./project/report/inverted_analytic_balance.py
./project/report/quantity_cost_ledger.py
./project/wizard/__init__.py
./project/wizard/account_analytic_balance_report.py
./project/wizard/account_analytic_chart.py
./project/wizard/account_analytic_cost_ledger_for_journal_report.py
./project/wizard/account_analytic_cost_ledger_report.py
./project/wizard/account_analytic_inverted_balance_report.py
./project/wizard/account_analytic_journal_report.py
./project/wizard/project_account_analytic_line.py
./report/__init__.py
./report/account_aged_partner_balance.py
./report/account_analytic_entries_report.py
./report/account_balance.py
./report/account_central_journal.py
./report/account_entries_report.py
./report/account_financial_report.py
./report/account_general_journal.py
./report/account_general_ledger.py
./report/account_invoice_report.py
./report/account_journal.py
./report/account_partner_balance.py
./report/account_partner_ledger.py
./report/account_print_invoice.py
./report/account_print_overdue.py
openerp_account.egg-info/PKG-INFO
openerp_account.egg-info/SOURCES.txt
openerp_account.egg-info/dependency_links.txt
openerp_account.egg-info/requires.txt
openerp_account.egg-info/top_level.txt
